check_puppet_agent/__init__.py
check_puppet_agent-1.0.0.data/scripts/check-puppet-agent
check_puppet_agent-1.0.0.dist-info/DESCRIPTION.rst
check_puppet_agent-1.0.0.dist-info/METADATA
check_puppet_agent-1.0.0.dist-info/metadata.json
check_puppet_agent-1.0.0.dist-info/RECORD
check_puppet_agent-1.0.0.dist-info/top_level.txt
check_puppet_agent-1.0.0.dist-info/WHEEL
