Metadata-Version: 2.0
Name: check-puppet-agent
Version: 1.0.0
Summary: A check to monitor puppet agent runs
Home-page: https://github.com/wywygmbh/check-puppet-agent
Author: Christian Becker
Author-email: christian.becker@wywy.com
License: GPLv2
Platform: any
Classifier: Environment :: Console
Classifier: Intended Audience :: System Administrators
Classifier: License :: OSI Approved :: GNU General Public License v2 (GPLv2)
Classifier: Operating System :: OS Independent
Classifier: Programming Language :: Python
Classifier: Programming Language :: Python :: 2
Classifier: Programming Language :: Python :: 3
Classifier: Topic :: System :: Systems Administration
Requires-Dist: argparse
Requires-Dist: Pyaml
Requires-Dist: six
